[
    {
        "code": "11008",
        "name": "Paddy (Neang Khon)",
        "prices": [
            {
                "date": "2018-02-05 00:00:00",
                "id": 842530,
                "price": "923.00"
            },
            {
                "date": "2018-02-07 00:00:00",
                "id": 842705,
                "price": "922.00"
            },
            {
                "date": "2018-02-28 00:00:00",
                "id": 842713,
                "price": "922.00"
            },
            {
                "date": "2018-06-13 00:00:00",
                "id": 1000018,
                "price": "923.00"
            },
            {
                "date": "2019-01-09 00:00:00",
                "id": 1057645,
                "price": "875.00"
            },
            {
                "date": "2019-01-16 00:00:00",
                "id": 1059847,
                "price": "1134.00"
            },
            {
                "date": "2019-01-23 00:00:00",
                "id": 1063046,
                "price": "1134.00"
            },
            {
                "date": "2019-01-30 00:00:00",
                "id": 1066285,
                "price": "1085.00"
            },
            {
                "date": "2019-02-06 00:00:00",
                "id": 1068826,
                "price": "1085.00"
            },
            {
                "date": "2019-02-13 00:00:00",
                "id": 1072344,
                "price": "1085.00"
            },
            {
                "date": "2019-02-20 00:00:00",
                "id": 1074686,
                "price": "1000.00"
            },
            {
                "date": "2019-02-27 00:00:00",
                "id": 1078042,
                "price": "1085.00"
            },
            {
                "date": "2019-03-13 00:00:00",
                "id": 1084040,
                "price": "1085.00"
            },
            {
                "date": "2019-03-20 00:00:00",
                "id": 1087028,
                "price": "1080.00"
            },
            {
                "date": "2019-03-27 00:00:00",
                "id": 1089599,
                "price": "1070.00"
            },
            {
                "date": "2019-04-10 00:00:00",
                "id": 1094411,
                "price": "1070.00"
            },
            {
                "date": "2019-04-24 00:00:00",
                "id": 1097956,
                "price": "1070.00"
            },
            {
                "date": "2019-05-08 00:00:00",
                "id": 1102851,
                "price": "1070.00"
            },
            {
                "date": "2019-06-12 00:00:00",
                "id": 1113149,
                "price": "1070.00"
            },
            {
                "date": "2019-12-25 00:00:00",
                "id": 1176572,
                "price": "871.00"
            },
            {
                "date": "2020-01-08 00:00:00",
                "id": 1181986,
                "price": "831.00"
            },
            {
                "date": "2020-01-15 00:00:00",
                "id": 1184202,
                "price": "831.00"
            },
            {
                "date": "2020-01-22 00:00:00",
                "id": 1186446,
                "price": "831.00"
            },
            {
                "date": "2020-01-29 00:00:00",
                "id": 1189174,
                "price": "831.00"
            },
            {
                "date": "2020-02-12 00:00:00",
                "id": 1195141,
                "price": "831.00"
            },
            {
                "date": "2020-02-19 00:00:00",
                "id": 1196814,
                "price": "831.00"
            },
            {
                "date": "2020-03-04 00:00:00",
                "id": 1202380,
                "price": "831.00"
            },
            {
                "date": "2020-03-11 00:00:00",
                "id": 1212104,
                "price": "1070.00"
            },
            {
                "date": "2020-03-18 00:00:00",
                "id": 1212176,
                "price": "1070.00"
            },
            {
                "date": "2020-03-25 00:00:00",
                "id": 1212153,
                "price": "1070.00"
            }
        ]
    }
]